OpenFG/__init__.py
OpenFG/code.py
OpenFG-0.1.0.dist-info/METADATA
OpenFG-0.1.0.dist-info/WHEEL
OpenFG-0.1.0.dist-info/top_level.txt
OpenFG-0.1.0.dist-info/RECORD
