Metadata-Version: 2.1
Name: OpenFG
Version: 0.1.0
Summary: Library for work with our api.
Home-page: https://github.com/kararasenok-gd/krrsnkapi
Author: Kararasenok =), KailUser
License: MIT
Classifier: Intended Audience :: Developers
Classifier: License :: OSI Approved :: MIT License
Classifier: Programming Language :: Python
Classifier: Programming Language :: Python :: 3
Classifier: Programming Language :: Python :: 3.6
Classifier: Programming Language :: Python :: 3.7
Classifier: Programming Language :: Python :: 3.8
Classifier: Programming Language :: Python :: 3.9
Classifier: Operating System :: OS Independent
